mibbridge/__init__.py
mibbridge/__main__.py
mibbridge/bridge.py
mibbridge/cli.py
mibbridge-0.1.dist-info/METADATA
mibbridge-0.1.dist-info/WHEEL
mibbridge-0.1.dist-info/entry_points.txt
mibbridge-0.1.dist-info/licenses/LICENCE
mibbridge-0.1.dist-info/RECORD
